repominify/__init__.py
repominify/cli.py
repominify/constants.py
repominify/dependencies.py
repominify/exceptions.py
repominify/exporters.py
repominify/formatters.py
repominify/graph.py
repominify/logging.py
repominify/parser.py
repominify/stats.py
repominify/types.py
repominify-0.1.6.dist-info/LICENSE
repominify-0.1.6.dist-info/METADATA
repominify-0.1.6.dist-info/WHEEL
repominify-0.1.6.dist-info/entry_points.txt
repominify-0.1.6.dist-info/top_level.txt
repominify-0.1.6.dist-info/RECORD
