Metadata-Version: 2.1
Name: repominify
Version: 0.1.6
Summary: A Python package that optimizes codebase representations for LLMs by generating compact, context-rich summaries
Home-page: https://github.com/mikewcasale/repominify
Author: Mike Casale
Author-email: mike@casale.xyz
Classifier: Development Status :: 3 - Alpha
Classifier: Intended Audience :: Developers
Classifier: License :: OSI Approved :: MIT License
Classifier: Programming Language :: Python :: 3
Classifier: Programming Language :: Python :: 3.7
Classifier: Programming Language :: Python :: 3.8
Classifier: Programming Language :: Python :: 3.9
Classifier: Programming Language :: Python :: 3.10
Requires-Python: >=3.7
License-File: LICENSE
Requires-Dist: networkx>=2.6.0
Requires-Dist: pyyaml>=5.1.0
